device_selector/__init__.py
device_selector/device_selector.py
test/test_device_selector.py
device_selector-0.1.0.dist-info/METADATA
device_selector-0.1.0.dist-info/WHEEL
device_selector-0.1.0.dist-info/top_level.txt
device_selector-0.1.0.dist-info/RECORD
