Metadata-Version: 2.2
Name: device-selector
Version: 0.1.0
Summary: A utility library to select and handle devices (CPU/GPU) seamlessly.
Author-email: Daniel Ariza <danielarizae@gmail.com>
License: MIT
Classifier: Programming Language :: Python :: 3
Classifier: Programming Language :: Python :: 3.10
Classifier: Programming Language :: Python :: 3.11
Classifier: License :: OSI Approved :: MIT License
Classifier: Operating System :: OS Independent
Requires-Python: <3.12,>=3.10
Requires-Dist: torch<3.0,>=2.0
Provides-Extra: test
Requires-Dist: pytest>=7.0; extra == "test"
